casualty/__init__.py
casualty/casualty_logger.py
casualty/constants.py
casualty/django_corelation_middleware.py
casualty/filter.py
casualty/flask_corelation_middleware.py
casualty/patcher.py
casualty/ext/__init__.py
casualty/ext/kombu/__init__.py
casualty/ext/kombu/patch.py
casualty/ext/requests/__init__.py
casualty/ext/requests/patch.py
tests/ext/__init__.py
tests/ext/test_kombu.py
tests/ext/test_request.py
casualty-0.1.9.dist-info/LICENSE
casualty-0.1.9.dist-info/METADATA
casualty-0.1.9.dist-info/WHEEL
casualty-0.1.9.dist-info/top_level.txt
casualty-0.1.9.dist-info/RECORD
