Metadata-Version: 2.1
Name: casualty
Version: 0.1.9
Summary: A python library to generate co-relation id and bind it to headers in outgoing request
Home-page: UNKNOWN
Author: Sohit Kumar
Author-email: sumitk002@gmail.com
License: MIT
Platform: UNKNOWN
Requires-Python: >=2.6, !=3.0.*, !=3.1.*, !=3.2.*, !=3.3.*
Requires-Dist: structlog (==18.2.0)
Requires-Dist: wrapt (==1.10.11)
Requires-Dist: pre-commit-hooks (==1.4.0)
Requires-Dist: mock (==2.0.0)
Requires-Dist: pytest (==3.8.2)
Requires-Dist: pytest-mock (==1.10.0)
Requires-Dist: pytest-cov
